guitares/__init__.py
guitares/colormap.py
guitares/dependencies.py
guitares/dialog.py
guitares/element.py
guitares/gui.py
guitares/menu.py
guitares/server.py
guitares/window.py
guitares/img/Check_mark_23x20_02.svg.png
guitares/img/black_down_48x48.png
guitares/img/black_left_48x48.png
guitares/img/black_right_48x48.png
guitares/img/black_up_48x48.png
guitares/img/category_1_hurricane_icon_24x48.png
guitares/img/category_2_hurricane_icon_24x48.png
guitares/img/category_3_hurricane_icon_24x48.png
guitares/img/category_4_hurricane_icon_24x48.png
guitares/img/category_5_hurricane_icon_24x48.png
guitares/img/icons8-triangle-arrow-16_white_down.png
guitares/img/icons8-triangle-arrow-16_white_left.png
guitares/img/icons8-triangle-arrow-16_white_right.png
guitares/img/icons8-triangle-arrow-16_white_up.png
guitares/img/icons8-triangle-arrow-24_black_down.png
guitares/img/icons8-triangle-arrow-24_black_left.png
guitares/img/icons8-triangle-arrow-24_black_right.png
guitares/img/icons8-triangle-arrow-24_black_up.png
guitares/img/icons8-triangle-arrow-24_white_left.png
guitares/img/icons8-triangle-arrow-24_white_right.png
guitares/img/mapbox-marker-icon-20px-blue.png
guitares/img/mapbox-marker-icon-20px-gray.png
guitares/img/mapbox-marker-icon-20px-green.png
guitares/img/mapbox-marker-icon-20px-orange.png
guitares/img/mapbox-marker-icon-20px-pink.png
guitares/img/mapbox-marker-icon-20px-purple.png
guitares/img/mapbox-marker-icon-20px-red.png
guitares/img/mapbox-marker-icon-20px-yellow.png
guitares/img/tide_icon_48x48.png
guitares/img/tropical_storm_icon_24x48.png
guitares/img/vector-checkmark-icon_905002-20.png
guitares/img/white_down_48x48.png
guitares/img/white_left_48x48.png
guitares/img/white_right_48x48.png
guitares/img/white_up_48x48.png
guitares/map/__init__.py
guitares/map/choropleth_layer.py
guitares/map/circle_layer.py
guitares/map/circle_selector_layer.py
guitares/map/colorbar.py
guitares/map/cyclone_track_layer.py
guitares/map/datashader_choropleth_layer.py.old
guitares-0.1.5.dist-info/licenses/LICENSE
guitares-0.1.5.dist-info/METADATA
guitares-0.1.5.dist-info/WHEEL
guitares-0.1.5.dist-info/top_level.txt
guitares-0.1.5.dist-info/RECORD
